LICENSE.txt
MANIFEST.in
README.md
setup.py
msgpackpyc/include/Event.h
msgpackpyc/include/EventType.h
msgpackpyc/include/EventVal.h
msgpackpyc/include/ExtType.h
msgpackpyc/include/Format.h
msgpackpyc/include/HeaderUtil.h
msgpackpyc/include/ParserInfo.h
msgpackpyc/include/ParserState.h
msgpackpyc/include/ScannerState.h
msgpackpyc/include/SegmentType.h
msgpackpyc/include/Template.h
msgpackpyc/include/ValueType.h
msgpackpyc/include/unpacker.h
msgpackpyc/src/Event.cpp
msgpackpyc/src/ExtType.cpp
msgpackpyc/src/HeaderUtil.cpp
msgpackpyc/src/ParserInfo.cpp
msgpackpyc/src/ParserState.cpp
msgpackpyc/src/unpacker.cpp
msgpackpyc/src/unpackerapi.cpp
msgpackstream/__init__.py
msgpackstream/defs.py
msgpackstream/errors.py
msgpackstream/stream.py
msgpackstream.egg-info/PKG-INFO
msgpackstream.egg-info/SOURCES.txt
msgpackstream.egg-info/dependency_links.txt
msgpackstream.egg-info/requires.txt
msgpackstream.egg-info/top_level.txt
msgpackstream/backend/__init__.py
msgpackstream/backend/pyc/__init__.py
msgpackstream/backend/pyc/stream.py
msgpackstream/backend/python/__init__.py
msgpackstream/backend/python/format.py
msgpackstream/backend/python/stream.py