Metadata-Version: 1.1
Name: msgpackstream
Version: 1.2.7
Summary: A SAX-like MessagegPack library in python to deserialize messages from an input stream
Home-page: https://github.com/salimm/msgpack-pystream
Author: Salim Malakouti
Author-email: salim.malakouti@gmail.com
License: MIT
Download-URL: http://github.com/salimm/msgpack-pystream/archive/1.2.7.tar.gz
Keywords: python,msgpack,serialization,binary,fast
Platform: UNKNOWN
Classifier: Programming Language :: Python
